oauthost/__init__.py
oauthost/admin.py
oauthost/apps.py
oauthost/auth_handlers.py
oauthost/decorators.py
oauthost/endpoints.py
oauthost/exceptions.py
oauthost/fields.py
oauthost/models.py
oauthost/settings.py
oauthost/toolbox.py
oauthost/urls.py
oauthost/utils.py
oauthost/views.py
oauthost/locale/en/LC_MESSAGES/django.po
oauthost/locale/ru/LC_MESSAGES/django.mo
oauthost/locale/ru/LC_MESSAGES/django.po
oauthost/management/__init__.py
oauthost/management/__init__.pyc
oauthost/management/__pycache__/__init__.cpython-33.pyc
oauthost/management/__pycache__/__init__.cpython-34.pyc
oauthost/management/__pycache__/__init__.cpython-35.pyc
oauthost/management/__pycache__/__init__.cpython-36.pyc
oauthost/management/__pycache__/__init__.cpython-38.pyc
oauthost/management/commands/__init__.py
oauthost/management/commands/__init__.pyc
oauthost/management/commands/syncscopes.py
oauthost/management/commands/syncscopes.pyc
oauthost/management/commands/__pycache__/__init__.cpython-35.pyc
oauthost/management/commands/__pycache__/__init__.cpython-36.pyc
oauthost/migrations/0001_initial.py
oauthost/migrations/0001_initial.pyc
oauthost/migrations/0002_auto_20150927_1933.py
oauthost/migrations/0002_auto_20150927_1933.pyc
oauthost/migrations/__init__.py
oauthost/migrations/__init__.pyc
oauthost/migrations/__pycache__/0001_initial.cpython-34.pyc
oauthost/migrations/__pycache__/0001_initial.cpython-35.pyc
oauthost/migrations/__pycache__/0001_initial.cpython-36.pyc
oauthost/migrations/__pycache__/0001_initial.cpython-38.pyc
oauthost/migrations/__pycache__/0002_auto_20150927_1933.cpython-34.pyc
oauthost/migrations/__pycache__/0002_auto_20150927_1933.cpython-35.pyc
oauthost/migrations/__pycache__/0002_auto_20150927_1933.cpython-36.pyc
oauthost/migrations/__pycache__/0002_auto_20150927_1933.cpython-38.pyc
oauthost/migrations/__pycache__/__init__.cpython-34.pyc
oauthost/migrations/__pycache__/__init__.cpython-35.pyc
oauthost/migrations/__pycache__/__init__.cpython-36.pyc
django_oauthost-1.1.1.dist-info/AUTHORS
django_oauthost-1.1.1.dist-info/LICENSE
django_oauthost-1.1.1.dist-info/METADATA
django_oauthost-1.1.1.dist-info/WHEEL
django_oauthost-1.1.1.dist-info/top_level.txt
django_oauthost-1.1.1.dist-info/RECORD
